{
  "code": 1,
  "popular_top": [
    {
      "popularName": "甜甜圈",
      "num": 1765,
      "ids": 1,
      "name": "雨露",
      "src":"./images/foods_03.jpg"
    },

    {
      "popularName": "番茄鸡蛋",
      "num": 1765,
      "ids": 2,
      "name": "方求",
      "src":"./images/foods_05.jpg"
    },
    {
      "popularName": "桑葚蛋糕",
      "num": 1765,
      "ids": 3,
      "name": "亲亲出发",
      "src":"./images/foods_09.jpg"
    },

    {
      "popularName": "奶露蛋糕",
      "num": 1765,
      "ids": 4,
      "name": "小菲菲是我",
      "src":"./images/foods_10.jpg"
    },
    {
      "popularName": "甜甜圈",
      "num": 1765,
      "ids": 5,
      "name": "雨露",
      "src":"./images/foods_03.jpg"
    },

    {
      "popularName": "番茄鸡蛋",
      "num": 1765,
      "ids":6,
      "name": "方求",
      "src":"./images/foods_05.jpg"
    },
    {
      "popularName": "桑葚蛋糕",
      "num": 1765,
      "ids": 7,
      "name": "亲亲出发",
      "src":"./images/foods_09.jpg"
    },

    {
      "popularName": "奶露蛋糕",
      "num": 1765,
      "ids": 8,
      "name": "小菲菲是我",
      "src":"./images/foods_10.jpg"
    },
    {
      "popularName": "奶露蛋糕",
      "num": 1765,
      "ids": 8,
      "name": "小菲菲是我",
      "src":"./images/foods_10.jpg"
    },
    {
      "popularName": "奶露蛋糕",
      "num": 1765,
      "ids": 8,
      "name": "小菲菲是我",
      "src":"./images/foods_10.jpg"
    }
  ]

}